zutool/__init__.py
zutool/api.py
zutool/main.py
zutool/py.typed
zutool/models/__init__.py
zutool/models/dict.py
zutool/models/enum_type.py
zutool/models/error.py
zutool/models/get_otenki_asp.py
zutool/models/get_pain_status.py
zutool/models/get_weather_point.py
zutool/models/get_weather_status.py
zutool/models/set_weather_point.py
zutool-0.2.1.dist-info/METADATA
zutool-0.2.1.dist-info/WHEEL
zutool-0.2.1.dist-info/entry_points.txt
zutool-0.2.1.dist-info/licenses/LICENSE.txt
zutool-0.2.1.dist-info/RECORD
