Metadata-Version: 2.4
Name: zutool
Version: 0.2.1
Summary: Unofficial zutool (頭痛ール: https://zutool.jp/) API Wrapper
Project-URL: Repository, https://github.com/eggplants/zutool
Author-email: eggplants <w10776e8w@yahoo.co.jp>
License: MIT
License-File: LICENSE.txt
Keywords: zutool
Classifier: License :: OSI Approved :: MIT License
Classifier: Programming Language :: Python :: 3 :: Only
Classifier: Programming Language :: Python :: 3.9
Classifier: Programming Language :: Python :: 3.10
Classifier: Programming Language :: Python :: 3.11
Classifier: Programming Language :: Python :: 3.12
Classifier: Programming Language :: Python :: 3.13
Classifier: Typing :: Typed
Requires-Python: <4,>=3.9
Requires-Dist: pydantic<3,>=2.10.5
Requires-Dist: requests<3,>=2.32.3
Requires-Dist: rich<14,>=13.9.4
